distributed_agent_mesh/__init__.py
distributed_agent_mesh-0.1.0.dist-info/licenses/LICENSE
distributed_agent_mesh-0.1.0.dist-info/METADATA
distributed_agent_mesh-0.1.0.dist-info/WHEEL
distributed_agent_mesh-0.1.0.dist-info/top_level.txt
distributed_agent_mesh-0.1.0.dist-info/RECORD
