Metadata-Version: 2.4
Name: distributed-agent-mesh
Version: 0.1.0
Summary: A framework for autonomous agents that collaborate via P2P communication
Home-page: https://github.com/Kumar123ips/distributed-agent-mesh
Author: Abhishek Kumar
Author-email: Abhishek Kumar <ipsabhi420@gmail.com>
License: MIT
Project-URL: Homepage, https://github.com/Kumar123ips/distributed-agent-mesh
Project-URL: Documentation, https://github.com/Kumar123ips/distributed-agent-mesh#readme
Project-URL: Repository, https://github.com/Kumar123ips/distributed-agent-mesh
Project-URL: Bug Tracker, https://github.com/Kumar123ips/distributed-agent-mesh/issues
Keywords: agents,distributed,p2p,autonomous,collaboration,mesh,multi-agent,ai
Classifier: Development Status :: 3 - Alpha
Classifier: Intended Audience :: Developers
Classifier: Topic :: Software Development :: Libraries :: Application Frameworks
Classifier: Topic :: Scientific/Engineering :: Artificial Intelligence
Classifier: License :: OSI Approved :: MIT License
Classifier: Programming Language :: Python :: 3
Classifier: Programming Language :: Python :: 3.8
Classifier: Programming Language :: Python :: 3.9
Classifier: Programming Language :: Python :: 3.10
Classifier: Programming Language :: Python :: 3.11
Classifier: Programming Language :: Python :: 3.12
Requires-Python: >=3.8
License-File: LICENSE
Provides-Extra: dev
Requires-Dist: pytest>=7.0.0; extra == "dev"
Requires-Dist: pytest-asyncio>=0.21.0; extra == "dev"
Requires-Dist: black>=22.0.0; extra == "dev"
Requires-Dist: flake8>=5.0.0; extra == "dev"
Requires-Dist: mypy>=0.990; extra == "dev"
Dynamic: author
Dynamic: home-page
Dynamic: license-file
Dynamic: requires-python
